MANIFEST.in
setup.cfg
setup.py
hotweb/__init__.py
hotweb/hotweb.py
hotweb/routes.py
hotweb/server.py
hotweb/test.py
hotweb/waitress_server.py
hotweb.egg-info/PKG-INFO
hotweb.egg-info/SOURCES.txt
hotweb.egg-info/dependency_links.txt
hotweb.egg-info/requires.txt
hotweb.egg-info/top_level.txt
hotweb/api/__init__.py
hotweb/api/api.py
hotweb/api/body.py
hotweb/api/compless.py
hotweb/api/constants.py
hotweb/api/footer.py
hotweb/api/forloop.py
hotweb/api/headContent.py
hotweb/api/if_.py
hotweb/dom/__init__.py
hotweb/dom/dom.js
hotweb/dom/dom.json
hotweb/dom/domFunction.py
hotweb/dom/dom_.py
hotweb/exceptions/__init__.py
hotweb/exceptions/exceptions.py
hotweb/models/__init__.py
hotweb/models/constants.py
hotweb/models/exceptions.py
hotweb/models/models.py
hotweb/models/query_sql.py
hotweb/models/skel_example.py
hotweb/models/skeleton.py
hotweb/router/__init__.py
hotweb/router/route_.py
hotweb/shortcuts/__init__.py
hotweb/shortcuts/load_file.py
hotweb/temp/__init__.py
hotweb/temp/test.html
hotweb/uix/__init__.py
hotweb/uix/index.py
hotweb/uix/test.html
hotweb/uix/Accordion/__init__.py
hotweb/uix/Alert/__init__.py
hotweb/uix/Avatar/__init__.py
hotweb/uix/Badge/__init__.py
hotweb/uix/Bottomnavigarion/__init__.py
hotweb/uix/Box/__init__.py
hotweb/uix/Breadcrumps/__init__.py
hotweb/uix/Button/__init__.py
hotweb/uix/Card/__init__.py
hotweb/uix/Darkmode/__init__.py
hotweb/uix/Divider/__init__.py
hotweb/uix/Drawer/__init__.py
hotweb/uix/Fab/__init__.py
hotweb/uix/Form/__init__.py
hotweb/uix/Form/form.py
hotweb/uix/Icon/__init__.py
hotweb/uix/Icons/__init__.py
hotweb/uix/Image/__init__.py
hotweb/uix/Input/__init__.py
hotweb/uix/Link/__init__.py
hotweb/uix/Link/link.py
hotweb/uix/List/__init__.py
hotweb/uix/Menu/__init__.py
hotweb/uix/Modal/__init__.py
hotweb/uix/Nav/__init__.py
hotweb/uix/Pagination/__init__.py
hotweb/uix/Paper/__init__.py
hotweb/uix/Progress/__init__.py
hotweb/uix/Rating/__init__.py
hotweb/uix/Skeleton/__init__.py
hotweb/uix/Slider/__init__.py
hotweb/uix/Snackbar/__init__.py
hotweb/uix/Speeddial/__init__.py
hotweb/uix/Stepper/__init__.py
hotweb/uix/Switch/__init__.py
hotweb/uix/Table/__init__.py
