Metadata-Version: 2.1
Name: hotweb
Version: 0.7.183
Author: Real Manlow,aka ManlowCharumbira
Author-email: realmanlow20@gmail.com
License: MIT
Keywords: hotweb python-web-framework python web framework fast light secure
